README.md
setup.py
protencoder/__init__.py
protencoder.egg-info/PKG-INFO
protencoder.egg-info/SOURCES.txt
protencoder.egg-info/dependency_links.txt
protencoder.egg-info/not-zip-safe
protencoder.egg-info/requires.txt
protencoder.egg-info/top_level.txt